tf_text_model/__init__.py
tf_text_model/bert_embedding.py
tf_text_model/bert_tokenizer.py
tf_text_model/classifier.py
tf_text_model/model_wrapper.py
tf_text_model/text_transformer.py
tf_text_model/version.txt
tf_text_model-0.0.14.dist-info/LICENSE
tf_text_model-0.0.14.dist-info/METADATA
tf_text_model-0.0.14.dist-info/WHEEL
tf_text_model-0.0.14.dist-info/top_level.txt
tf_text_model-0.0.14.dist-info/RECORD
